{
  "total": 27,
  "items": [
    {
      "id": "625359e0-1bb2-4eed-b64a-ba66966c13d9",
      "name": "Sinh phẩm dùng xác định nhóm máu Rh (D).",
      "model": "822001",
      "brand": "Thuốc thử xét nghiệm định danh nhóm máu type Rho (D)\r\n(Anti-D (Rho) Plus Monoclonal IgM & IgG Blood Grouping Reagent)",
      "manufacturer": "Egyptian Company for Biotechnology (S.A.E) – Spectrum Diagnostics/ Ai Cập",
      "origin": "Ai Cập",
      "manufactureYear": "Từ năm 2025 trở về sau",
      "specification": "Sinh phẩm dùng xác định nhóm máu Rh (D)/Anti-D (IgM+IgG). Phát hiện typ Rho (D). Lọ 10ml.",
      "unit": "Lọ",
      "quantity": 10,
      "unitPrice": 167200,
      "winnerNames": [
        "CÔNG TY CỔ PHẦN DƯỢC PHẨM TƯỜNG KHUÊ"
      ],
      "decisionNo": "291/QĐ-TTYT",
      "decisionDate": "2026-06-04T15:45:38",
      "resultPublishedDate": "2026-06-04T15:46:52"
    },
    {
      "id": "f9f0f3b0-e3af-4d7f-9d09-f6a3c5d979f2",
      "name": "Mask ampu",
      "model": "BBP-E",
      "brand": "BBP-E",
      "manufacturer": "Công ty cổ phần Đất Việt Thành/\r\nViệt Nam",
      "origin": "Việt Nam",
      "manufactureYear": "2025\r\n trở\r\n về\r\n sau",
      "specification": "Mask ampu có vành bơm hơi, vòng đệm có van để bơm hơi. Cỡ số 4-5; Chất liệu PVC hoặc PE . Quy cách đóng gói: túi  01 cái",
      "unit": "Cái",
      "quantity": 50,
      "unitPrice": 25000,
      "winnerNames": [
        "CÔNG TY CỔ PHẦN AK GLOBAL VIỆT NAM"
      ],
      "decisionNo": "291/QĐ-TTYT",
      "decisionDate": "2026-06-04T15:45:38",
      "resultPublishedDate": "2026-06-04T15:46:52"
    },
    {
      "id": "d2a4ce53-cd27-46f2-8746-095b0bea3257",
      "name": "Khai mở khí quản có bóng (Canuyn mở khí quản có bóng) các số",
      "model": "Tracheost omy tube",
      "brand": "Tracheost omy tube",
      "manufacturer": "Ningbo \r\nGreetmed \r\nMedical \r\nInstruments \r\nCo., Ltd/ \r\nTrung Quốc",
      "origin": "Trung Quốc",
      "manufactureYear": "2025 trở về sau",
      "specification": "Ống mở khí quản với thiết kế có bóng trong có thể tháo rời để làm sạch, tránh nghẹt tắc \r\nđờm. \r\n Chất liệu PVC mềm không gây kích ứng và dễ thích nghi với nhiệt độ cơ thể giúp bệnh \r\nnhân cảm thấy thoải mái. \r\n Có góc cong 90 độ, cổng kết nối tiêu chuẩn 15mm, có van nhựa đầu ống. \r\n Có bóng thề tích lớn, áp suất nhỏ, đường cản quang dọc thân ống. \r\n Size: 3,4, 4.5, 5, 5.5, 6, 6.5, 7, 7.5, 8.0, 8.5, 9.0. \r\n Sản phẩm tiệt trùng từng cái, dùng 1 lần. \r\n Hạn dùng: 5 năm kể từ ngày sản xuất.",
      "unit": "Cái",
      "quantity": 30,
      "unitPrice": 61000,
      "winnerNames": [
        "CÔNG TY TNHH THƯƠNG MẠI DỊCH VỤ TỔNG HỢP BẢO HÂN"
      ],
      "decisionNo": "291/QĐ-TTYT",
      "decisionDate": "2026-06-04T15:45:38",
      "resultPublishedDate": "2026-06-04T15:46:52"
    },
    {
      "id": "cb98180b-4188-447f-a6d8-29d098f36732",
      "name": "Nhiệt kế y tế thủy ngân",
      "model": "CRW-23",
      "brand": "CRW-23",
      "manufacturer": "Jiangsu Yuyue Medical Instruments Co.,Ltd",
      "origin": "Trung Quốc",
      "manufactureYear": "2025\r\n trở\r\n về\r\n sau",
      "specification": "Được làm từ thủy tinh trong suốt, bên trong có vạch chia độ và dải thủy ngân. Hộp 1 cái",
      "unit": "Cái",
      "quantity": 120,
      "unitPrice": 23030,
      "winnerNames": [
        "CÔNG TY TNHH THƯƠNG MẠI DỊCH VỤ TỔNG HỢP BẢO HÂN"
      ],
      "decisionNo": "291/QĐ-TTYT",
      "decisionDate": "2026-06-04T15:45:38",
      "resultPublishedDate": "2026-06-04T15:46:52"
    },
    {
      "id": "ce794e89-04d5-4df8-b141-dda84a3bdcf1",
      "name": "Gel điện tim",
      "model": "\r\nECG-0001",
      "brand": "ECG GEL",
      "manufacturer": "TURKUAZ \r\nSAGLIK \r\nHIZMETLERI \r\nMEDIKAL \r\nTEMIZLIK \r\nKIMYASAL \r\nURUNLER\r\nSAN. VE TIC. \r\nA.S./ \r\nTURKEY",
      "origin": "Turkuaz - Thổ Nhĩ kỳ",
      "manufactureYear": "2025",
      "specification": "Gel điện tim phù hợp điện cực máy điện tim, điện não, giúp bảo vệ bề mặt đầu dò \r\nsiêu âm, không muối không bị ăn mòn, không chứa formaldehyde, không mẫn cảm \r\nda, không gây rát da.\r\n• Thành phần: Deionized Water, Carbomer, TriEthanol Amine, MonoPropylene \r\nGlycol, Benzyl Alcohol, Methylchloroisothi-azolinone, Methylisothiazolinone. Tuýp 250ml",
      "unit": "Tuýp",
      "quantity": 20,
      "unitPrice": 19950,
      "winnerNames": [
        "CÔNG TY TNHH THƯƠNG MẠI DỊCH VỤ TỔNG HỢP BẢO HÂN"
      ],
      "decisionNo": "291/QĐ-TTYT",
      "decisionDate": "2026-06-04T15:45:38",
      "resultPublishedDate": "2026-06-04T15:46:52"
    },
    {
      "id": "16286034-f27d-4d91-842d-85f0a1984fa5",
      "name": "Bộ hóa chất chuẩn máy huyết học 5 thành phần bạch cầu 3 mức",
      "model": "DDC5DT3L\r\nDDC5DT3N\r\nDDC5DT3H",
      "brand": "Diagon Ltd.",
      "manufacturer": "Diagon Ltd./Hungary",
      "origin": "Hungary",
      "manufactureYear": "2025 trở về sau",
      "specification": "Hóa chất chuẩn máy xét nghiệm huyết học\r\nThành phần: chiết xuất từ máu động vật có vú khỏe mạnh chất bảo quản và chất ổn định tế bào \r\nBảo quản: từ 2 - 8 độ C\r\nỐng = 3ml\r\nTiêu chuẩn ISO13485",
      "unit": "Ống",
      "quantity": 18,
      "unitPrice": 1500000,
      "winnerNames": [
        "CÔNG TY TNHH MEDITECH AUTOMATION"
      ],
      "decisionNo": "291/QĐ-TTYT",
      "decisionDate": "2026-06-04T15:45:38",
      "resultPublishedDate": "2026-06-04T15:46:52"
    },
    {
      "id": "ab68dc02-212b-4953-aa25-0099e44b26f6",
      "name": "Băng cá nhân",
      "model": "GT100-100; GT100-110",
      "brand": "Greetmed",
      "manufacturer": "Greetmed/\r\nTrung Quốc",
      "origin": "Trung Quốc",
      "manufactureYear": "2025 trở về sau",
      "specification": "Kích thước 19mm x 72mm. Phủ keo; Chất liệu PVC, PE, cotton, nhựa, vải không dệt…; co giãn, không thấm nước.",
      "unit": "Miếng",
      "quantity": 4000,
      "unitPrice": 189,
      "winnerNames": [
        "CÔNG TY TNHH MTV YTECO"
      ],
      "decisionNo": "291/QĐ-TTYT",
      "decisionDate": "2026-06-04T15:45:38",
      "resultPublishedDate": "2026-06-04T15:46:52"
    },
    {
      "id": "5b313707-7758-416c-b558-2643f8027d67",
      "name": "Sinh phẩm xác định nhóm máu A",
      "model": "810001",
      "brand": "Thuốc thử xét nghiệm định danh nhóm máu ABO/Rh\r\n(Anti-A Monoclonal (IgM) Blood Grouping Reagents)",
      "manufacturer": "Egyptian Company for Biotechnology (S.A.E) – Spectrum Diagnostics/ Ai Cập",
      "origin": "Ai Cập",
      "manufactureYear": "Từ năm 2025 trở về sau",
      "specification": "Sinh phẩm xác định nhóm máu A (Anti-A, IgM). Xác định nhóm máu hệ ABO. Lọ 10ml.",
      "unit": "Lọ",
      "quantity": 40,
      "unitPrice": 103840,
      "winnerNames": [
        "CÔNG TY CỔ PHẦN DƯỢC PHẨM TƯỜNG KHUÊ"
      ],
      "decisionNo": "291/QĐ-TTYT",
      "decisionDate": "2026-06-04T15:45:38",
      "resultPublishedDate": "2026-06-04T15:46:52"
    },
    {
      "id": "129a5059-d2de-4798-8ad8-818b986eae9c",
      "name": "Sinh phẩm xác định nhóm máu AB",
      "model": "816001",
      "brand": "Thuốc thử xét nghiệm định danh nhóm máu ABO/Rh \r\n(Anti - AB (IgM))",
      "manufacturer": "Egyptian Company for Biotechnology (S.A.E) – Spectrum Diagnostics/ Ai Cập",
      "origin": "Ai Cập",
      "manufactureYear": "Từ năm 2025 trở về sau",
      "specification": "Sinh phẩm xác định nhóm máu AB (Anti-AB, IgM). Xác định nhóm máu hệ ABO. Lọ  10ml.",
      "unit": "Lọ",
      "quantity": 10,
      "unitPrice": 103840,
      "winnerNames": [
        "CÔNG TY CỔ PHẦN DƯỢC PHẨM TƯỜNG KHUÊ"
      ],
      "decisionNo": "291/QĐ-TTYT",
      "decisionDate": "2026-06-04T15:45:38",
      "resultPublishedDate": "2026-06-04T15:46:52"
    },
    {
      "id": "8429098d-1a19-46df-824e-ca4a1b256634",
      "name": "Ống ly tâm nhỏ có vạch chia (Ống Eppendorf)",
      "model": "GT204-326",
      "brand": "GT204-326",
      "manufacturer": "Taizhou \r\nKangjian \r\nMedical \r\nEquipments \r\nCo., Ltd/ \r\nTrung Quốc",
      "origin": "Trung Quốc",
      "manufactureYear": "2026",
      "specification": "Ống nghiệm ly tâm xét nghiệm: * Thể tich chữa mẫu 1,5ml. * Chất liệu nhựa dùng trong y tế. * Đáy nhọn, nắp bật",
      "unit": "Ống",
      "quantity": 10000,
      "unitPrice": 240.1,
      "winnerNames": [
        "CÔNG TY TNHH THƯƠNG MẠI DỊCH VỤ TỔNG HỢP BẢO HÂN"
      ],
      "decisionNo": "291/QĐ-TTYT",
      "decisionDate": "2026-06-04T15:45:38",
      "resultPublishedDate": "2026-06-04T15:46:52"
    },
    {
      "id": "a8e4b9d5-5c1b-47d8-9f19-e84c6a34e799",
      "name": "Bộ bơm tiêm thuốc cản quang 1 nòng",
      "model": "AT 2204",
      "brand": "Anntom",
      "manufacturer": "Anntom Medica Limited./ Trung Quốc ",
      "origin": "Trung Quốc ",
      "manufactureYear": "Từ năm 2025 trở lên",
      "specification": "Bộ bơm tiêm 1 nòng áp lực cao dùng cho máy tiêm thuốc cản quang trong kỹ thuật chụp cắt lớp vi tính (CT):\r\nGồm:\r\n- 1 bơm tiêm (xilanh) 200 ml.\r\n- Dây áp lực dài 150 cm.\r\n- 1 ống lấy thuốc.\r\n- Tiệt trùng: EO.\r\nTiêu chuẩn: ISO 13485, CE",
      "unit": "Bộ",
      "quantity": 100,
      "unitPrice": 200000,
      "winnerNames": [
        "CÔNG TY TNHH PHƯỚC PHÁT EAKAO"
      ],
      "decisionNo": "291/QĐ-TTYT",
      "decisionDate": "2026-06-04T15:45:38",
      "resultPublishedDate": "2026-06-04T15:46:52"
    },
    {
      "id": "a9e24e02-c02d-43bf-a940-525ba206e17c",
      "name": "Dây Garo",
      "model": "DAYGR-02",
      "brand": "DAYGR-02",
      "manufacturer": "Công ty cổ phần Đất Việt Thành/ Việt Nam",
      "origin": "Việt Nam",
      "manufactureYear": "2025 trở\r\n về sau",
      "specification": "Chất liệu thun cotton, dài ≥28cm, rộng ≥2,5cm có khóa và dính băng dính 2 đầu.",
      "unit": "Cái",
      "quantity": 400,
      "unitPrice": 4000,
      "winnerNames": [
        "CÔNG TY CỔ PHẦN SINH"
      ],
      "decisionNo": "291/QĐ-TTYT",
      "decisionDate": "2026-06-04T15:45:38",
      "resultPublishedDate": "2026-06-04T15:46:52"
    },
    {
      "id": "fadef099-6116-46bd-b855-291367a1528d",
      "name": "Băng chỉ thị nhiệt hấp khô",
      "model": "PKPT1950",
      "brand": "Pakion",
      "manufacturer": "Jiangsu Pakion Medical Material Co., Ltd. - Trung Quốc ",
      "origin": "Trung Quốc",
      "manufactureYear": "Từ năm 2025 trở lên",
      "specification": "Giấy được in với mực chỉ thị dùng cho tiệt trùng bằng nhiệt (khô); Chất liệu: Cao su tự nhiên khô và chất kết dính nhựa. Độ bám dính tốt, lớp keo có độ dính cao. Sau tiệt trùng, các vạch chỉ thị sẽ chuyển sang màu khác.\r\nKích thước. 19mm x 50mm",
      "unit": "Cuộn",
      "quantity": 5,
      "unitPrice": 760000,
      "winnerNames": [
        "CÔNG TY TNHH PHƯỚC PHÁT EAKAO"
      ],
      "decisionNo": "291/QĐ-TTYT",
      "decisionDate": "2026-06-04T15:45:38",
      "resultPublishedDate": "2026-06-04T15:46:52"
    },
    {
      "id": "1e123411-ac2b-46c9-9706-0e524b9c836f",
      "name": "Sinh phẩm xác định nhóm máu B",
      "model": "814001",
      "brand": "Thuốc thử xét nghiệm định danh nhóm máu ABO/Rh \r\n(Anti - B (IgM))",
      "manufacturer": "Egyptian Company for Biotechnology (S.A.E) – Spectrum Diagnostics/ Ai Cập",
      "origin": "Ai Cập",
      "manufactureYear": "Từ năm 2025 trở về sau",
      "specification": "Sinh phẩm xác định nhóm máu B (Anti-B, IgM). Xác định nhóm máu hệ ABO. Lọ 10ml.",
      "unit": "Lọ",
      "quantity": 40,
      "unitPrice": 103840,
      "winnerNames": [
        "CÔNG TY CỔ PHẦN DƯỢC PHẨM TƯỜNG KHUÊ"
      ],
      "decisionNo": "291/QĐ-TTYT",
      "decisionDate": "2026-06-04T15:45:38",
      "resultPublishedDate": "2026-06-04T15:46:52"
    },
    {
      "id": "64df10c4-69b5-4e30-ad12-84235b7e3541",
      "name": "Khay inox",
      "model": "KINOX-02",
      "brand": "KINOX-02",
      "manufacturer": "Công ty cổ phần Vsens/\r\nViệt Nam",
      "origin": "Việt Nam",
      "manufactureYear": "2025\r\n trở\r\n về\r\n sau",
      "specification": "Chất liệu: Inox 304. Kích thước: (22cm x 32cm). Chiều cao từ 2cm-5cm. Sai số kích thước ±10%",
      "unit": "Cái",
      "quantity": 10,
      "unitPrice": 115000,
      "winnerNames": [
        "CÔNG TY CỔ PHẦN AK GLOBAL VIỆT NAM"
      ],
      "decisionNo": "291/QĐ-TTYT",
      "decisionDate": "2026-06-04T15:45:38",
      "resultPublishedDate": "2026-06-04T15:46:52"
    },
    {
      "id": "c732dcad-ae31-445b-bd4a-a7268876fce2",
      "name": "Giấy điện tim",
      "model": " 63 mm × 30 m ",
      "brand": "Tianjin ",
      "manufacturer": "Tianjin Grand\r\nPaper Industry\r\nCo., Ltd. - Trung Quốc ",
      "origin": "Trung Quốc",
      "manufactureYear": "Từ năm 2025 trở lên",
      "specification": "Giấy điện tim 3 cần. Kích thước 63 mm × 30 m (sai số: ±1 mm)",
      "unit": "Cuộn",
      "quantity": 200,
      "unitPrice": 18500,
      "winnerNames": [
        "CÔNG TY TNHH PHƯỚC PHÁT EAKAO"
      ],
      "decisionNo": "291/QĐ-TTYT",
      "decisionDate": "2026-06-04T15:45:38",
      "resultPublishedDate": "2026-06-04T15:46:52"
    },
    {
      "id": "39136864-11bb-4178-8687-1d862a2bb270",
      "name": "Băng dính vô trùng",
      "model": "VW6070(IV)",
      "brand": "PLAID",
      "manufacturer": "Công ty TNHH Young Chemical Vina/\r\nViệt Nam",
      "origin": "Việt Nam",
      "manufactureYear": "2025 trở về sau",
      "specification": "Băng dính vô trùng, vải không dệt, có rãnh chứ V với màng trong suốt không thấm nước, có gạc cố định kim luồn. Kích thước: 6cmx7cm.  \r\nĐóng gói tiệt trùng từng miếng riêng biệt.\r\n- Đạt Tiêu chuẩn: ISO 13485",
      "unit": "Miếng",
      "quantity": 2000,
      "unitPrice": 2300,
      "winnerNames": [
        "CÔNG TY TNHH MTV YTECO"
      ],
      "decisionNo": "291/QĐ-TTYT",
      "decisionDate": "2026-06-04T15:45:38",
      "resultPublishedDate": "2026-06-04T15:46:52"
    },
    {
      "id": "069e4266-dedb-4cd6-af21-024e2c9ebf73",
      "name": "Dây truyền máu",
      "model": "2002001",
      "brand": "Yudu",
      "manufacturer": "Suzhou Yudu/\r\nTrung Quốc",
      "origin": "Trung Quốc",
      "manufactureYear": "2025 trở về sau",
      "specification": "Dây truyền máu: Chất liệu nhựa dùng trong y tế/ PVC, chiều dài ≥ 150cm, màng lọc siêu nhỏ với kích thước lỗ lọc từ 175- 210µm..\r\n- Không có chất gây độc DEHP.\r\n- Được tiệt trùng, đóng gói từng cái. \r\n- Đạt tiêu chuẩn: ISO 13485.",
      "unit": "Cái",
      "quantity": 500,
      "unitPrice": 15000,
      "winnerNames": [
        "CÔNG TY TNHH MTV YTECO"
      ],
      "decisionNo": "291/QĐ-TTYT",
      "decisionDate": "2026-06-04T15:45:38",
      "resultPublishedDate": "2026-06-04T15:46:52"
    },
    {
      "id": "c1057b5d-86ff-40a0-93a8-9c663d409785",
      "name": "Kẹp mạch máu nội soi",
      "model": "ML",
      "brand": "ML",
      "manufacturer": "Qingdao DMD Medical Technology Co., LTD/ Trung Quốc",
      "origin": "Trung Quốc",
      "manufactureYear": "2025 trở\r\n về sau",
      "specification": "Clip kẹp mạch máu nội soi. Chất liệu titanium, hình chữ V, cấu tạo rãnh hình trái tim giúp clip bám chắc vào mạch máu, chân clip hình tam giác giúp tăng tối đa về mặt tiếp xúc giữa clip và hàm, bỏ hiện tượng rơi clip.",
      "unit": "Cái",
      "quantity": 30,
      "unitPrice": 63333.3333,
      "winnerNames": [
        "CÔNG TY CỔ PHẦN SINH"
      ],
      "decisionNo": "291/QĐ-TTYT",
      "decisionDate": "2026-06-04T15:45:38",
      "resultPublishedDate": "2026-06-04T15:46:52"
    },
    {
      "id": "f547820e-6957-40c0-ba21-20430df656bc",
      "name": "Vật liệu cầm máu",
      "model": "05180502",
      "brand": "CUTANPLAST",
      "manufacturer": "Mascia Brunelli/\r\nÝ",
      "origin": "Ý",
      "manufactureYear": "2025 trở về sau",
      "specification": "Chất liệu: gelatin dạng bọt xốp, tiệt trùng. Tự tiêu hoàn toàn. Kích thước: 8cm x 5cm x 1cm\r\nTiêu chuẩn: ISO 13485",
      "unit": "Cái",
      "quantity": 150,
      "unitPrice": 53900,
      "winnerNames": [
        "CÔNG TY TNHH MTV YTECO"
      ],
      "decisionNo": "291/QĐ-TTYT",
      "decisionDate": "2026-06-04T15:45:38",
      "resultPublishedDate": "2026-06-04T15:46:52"
    },
    {
      "id": "c84f1712-a99d-4326-9245-540b3f1c9654",
      "name": "Test xét nghiệm nhanh 5 trong 1 (cúm A,cúm B ,ADV, RSV, Covid-19)",
      "model": "GS110112C20",
      "brand": "GeneSign",
      "manufacturer": "GeneSign Biotech (Xiamen) Co.,Ltd",
      "origin": "Trung Quốc",
      "manufactureYear": "Từ 2025 trở về sau",
      "specification": "Là một xét nghiệm nhanh để phát hiện định tính SARS-CoV-2, vi rút cúm A, vi rút cúm B, vi rút hợp bào hô hấp và Adenovirus trong mẫu bệnh phẩm dịch tỵ hầu. Chỉ sử dụng cho chẩn đoán in vitro chuyên nghiệp. SARS-CoV-2: Độ nhạy tương quan: 98.37 % Độ đặc hiệu tương quan: 99.60% Độ chính xác tương quan: 98.81% - Cúm A: Độ nhạy tương quan: 99.50% Độ đặc hiệu tương quan: 99.90% Độ chính xác tương quan: 99.83% - Cúm B: Độ nhạy tương quan: 99.51% Độ đặc hiệu tương quan: 99.9% Độ chính xác tương quan: 99.84% - RSV: Độ nhạy tương quan: 96.06% Độ đặc hiệu tương quan: 98.86% Độ chính xác tương quan: 97.95% - Adenovirus: Độ nhạy tương quan: 96.94% Độ đặc hiệu tương quan: 99.67% Độ chính xác tương quan: 98.59%",
      "unit": "Test",
      "quantity": 200,
      "unitPrice": 50500,
      "winnerNames": [
        "CÔNG TY TNHH THIẾT BỊ VẬT TƯ ĐẶNG GIA"
      ],
      "decisionNo": "291/QĐ-TTYT",
      "decisionDate": "2026-06-04T15:45:38",
      "resultPublishedDate": "2026-06-04T15:46:52"
    },
    {
      "id": "2304f94a-7533-4274-8c8b-178852f33438",
      "name": "Test xét nghiệm (ASLO)",
      "model": "(ASOT) Latex",
      "brand": "(ASOT) Latex",
      "manufacturer": "Egyptian Company for Biotechnology (S.A.E)- Speetrum Diagnostics",
      "origin": "Ai Cập",
      "manufactureYear": "2026",
      "specification": "Test xét nghiệm vi khuẩn liên cầu (ASLO)",
      "unit": "Test",
      "quantity": 200,
      "unitPrice": 4410,
      "winnerNames": [
        "CÔNG TY TNHH THƯƠNG MẠI DỊCH VỤ TỔNG HỢP BẢO HÂN"
      ],
      "decisionNo": "291/QĐ-TTYT",
      "decisionDate": "2026-06-04T15:45:38",
      "resultPublishedDate": "2026-06-04T15:46:52"
    },
    {
      "id": "70bee55d-355f-4c5c-8f09-57dc081b844b",
      "name": "Bàn chải rửa tay phẫu thuật",
      "model": "ECO-BC",
      "brand": "ECO-BC",
      "manufacturer": "Công ty cổ phần Đất Việt Thành/ Việt Nam",
      "origin": "Việt Nam",
      "manufactureYear": "2025 trở\r\n về sau",
      "specification": "Chất liệu nhựa PP. Lông bàn chải làm bằng sợi cước nylon, đầu lông mềm. Kích thước: 4cm x 10cm. Có thể hấp tiệt trùng.",
      "unit": "Cái",
      "quantity": 200,
      "unitPrice": 28280,
      "winnerNames": [
        "CÔNG TY CỔ PHẦN SINH"
      ],
      "decisionNo": "291/QĐ-TTYT",
      "decisionDate": "2026-06-04T15:45:38",
      "resultPublishedDate": "2026-06-04T15:46:52"
    },
    {
      "id": "5a71a31b-48bf-4e0d-b3d4-2a027c897654",
      "name": "Cân trẻ sơ sinh",
      "model": "CĐHTE 20",
      "brand": "Nhơn Hòa",
      "manufacturer": "Nhơn Hòa/ Việt nam",
      "origin": "Việt Nam",
      "manufactureYear": "2025",
      "specification": "* Cấu hình gồm:  Cân trẻ em                       * Phạm vi đo: 500 g - 20 kg\r\n* Giá trị độ chia: 50 g\r\n* Sai số: \r\n+ Từ 500 g đến 2.5 kg: ± 25 g\r\n+ Từ 2.5 kg đến 10 kg: ± 50 g\r\n+ Từ 10 kg đến 20 kg: ± 75 g\r\n- Vỏ hộp cân và giá đỡ đĩa cân được sơn tĩnh điện.\r\n* Vỏ sắt sơn tĩnh điện.\r\n* Kích thước đĩa nhựa PP: (564 x 266x 80) mm\r\n* Mặt kính nhựa PC trong suốt.\r\n* Đường kính mặt số: 8 inches\r\n* Kích thước sản phẩm (D x R x C): (385 x 540 x 365) mm\r\n* Kích thước đóng gói đĩa cân: (560 x 275 x 102) mm\r\n* Thời hạn bảo hành: 12 tháng",
      "unit": "Cái",
      "quantity": 1,
      "unitPrice": 930000,
      "winnerNames": [
        "CÔNG TY TNHH THƯƠNG MẠI DỊCH VỤ TỔNG HỢP BẢO HÂN"
      ],
      "decisionNo": "291/QĐ-TTYT",
      "decisionDate": "2026-06-04T15:45:38",
      "resultPublishedDate": "2026-06-04T15:46:52"
    },
    {
      "id": "fed547d6-2638-41d4-98e4-698fd2f14d73",
      "name": "Kềm sinh thiết dùng trong nội soi",
      "model": "PTBF-2316BT, PTBF-2323BT",
      "brand": "Vicmed",
      "manufacturer": "Zhuji Pengtian Medical Instrument Co., Ltd/Trung Quốc",
      "origin": "Trung Quốc",
      "manufactureYear": "2025 trở về sau",
      "specification": "Đầu hình oval, loại không vỏ bọc, không kim, kẹp bằng răng cá sấu.\r\nKích thước: đường kính 2,3mm\r\nChiều dài làm việc: 160cm, 230cm\r\nTiêu chuẩn ISO 13485",
      "unit": "Cái",
      "quantity": 50,
      "unitPrice": 126000,
      "winnerNames": [
        "CÔNG TY CỔ PHẦN VẬT TƯ VÀ TRANG THIẾT BỊ Y TẾ CMD"
      ],
      "decisionNo": "291/QĐ-TTYT",
      "decisionDate": "2026-06-04T15:45:38",
      "resultPublishedDate": "2026-06-04T15:46:52"
    },
    {
      "id": "167d8874-f988-4aaf-b252-6a3b467eeddd",
      "name": "Khay inox",
      "model": "KINOX-01",
      "brand": "KINOX-01",
      "manufacturer": "Công ty cổ phần Vsens/\r\nViệt Nam",
      "origin": "Việt Nam",
      "manufactureYear": "2025\r\n trở\r\n về\r\n sau",
      "specification": "Chất liệu: Inox 304. Kích thước: (17cm x 22 cm x 2cm ). Sai số kích thước ±10%",
      "unit": "Cái",
      "quantity": 10,
      "unitPrice": 70000,
      "winnerNames": [
        "CÔNG TY CỔ PHẦN AK GLOBAL VIỆT NAM"
      ],
      "decisionNo": "291/QĐ-TTYT",
      "decisionDate": "2026-06-04T15:45:38",
      "resultPublishedDate": "2026-06-04T15:46:52"
    },
    {
      "id": "c1a08a67-6cc9-409b-86b1-594ff70d03a9",
      "name": "Kẹp mang kim",
      "model": "25-131",
      "brand": "25-132",
      "manufacturer": "Prime Tech Surgico/\r\nPakistan",
      "origin": "Pakistan",
      "manufactureYear": "2025\r\n trở\r\n về\r\n sau",
      "specification": "Kẹp kim phẫu thuật chất liệu thép không gỉ, kích thước 14-16cm.\r\n- Tiêu chuẩn: ISO 13485.",
      "unit": "Cái",
      "quantity": 10,
      "unitPrice": 38000,
      "winnerNames": [
        "CÔNG TY CỔ PHẦN AK GLOBAL VIỆT NAM"
      ],
      "decisionNo": "291/QĐ-TTYT",
      "decisionDate": "2026-06-04T15:45:38",
      "resultPublishedDate": "2026-06-04T15:46:52"
    }
  ],
  "fetchedAt": "2026-07-21T13:36:53.112Z"
}
